restparse/__init__.py
restparse/parser/__init__.py
restparse/parser/exceptions.py
restparse/parser/param.py
restparse/parser/params.py
restparse/parser/parser.py
tests/__init__.py
tests/test_parser.py
restparse-0.0.7.dist-info/LICENSE.txt
restparse-0.0.7.dist-info/METADATA
restparse-0.0.7.dist-info/WHEEL
restparse-0.0.7.dist-info/top_level.txt
restparse-0.0.7.dist-info/RECORD
