Metadata-Version: 2.1
Name: restparse
Version: 0.0.7
Summary: A simple, lightweight parser and validator for RESTful HTTP requests
Home-page: https://github.com/Julian-Nash/restparse
Author: Julian Nash
Author-email: julianjamesnash@gmail.com
License: UNKNOWN
Project-URL: Bug Tracker, https://github.com/Julian-Nash/restparse
Project-URL: Documentation, https://github.com/Julian-Nash/restparse
Project-URL: Source Code, https://github.com/Julian-Nash/restparse
Keywords: flask django request parser json rest
Platform: UNKNOWN
Classifier: Intended Audience :: Developers
Classifier: License :: OSI Approved :: MIT License
Classifier: Programming Language :: Python :: 3.6
Classifier: Programming Language :: Python :: 3.7
Classifier: Programming Language :: Python :: 3.8
